bridge.py
file_reader.py
main.py
amutils-0.0.3.dist-info/METADATA
amutils-0.0.3.dist-info/WHEEL
amutils-0.0.3.dist-info/entry_points.txt
amutils-0.0.3.dist-info/top_level.txt
amutils-0.0.3.dist-info/RECORD
