Metadata-Version: 2.2
Name: amutils
Version: 0.0.3
Summary: Apple Music Utilties
Home-page: https://github.com/realtvop/amutils
Author: realtvop
Classifier: Programming Language :: Python :: 3
Classifier: Operating System :: MacOS
Requires-Python: >=3.6
Requires-Dist: appscript
Requires-Dist: mutagen
Dynamic: author
Dynamic: classifier
Dynamic: description
Dynamic: description-content-type
Dynamic: home-page
Dynamic: requires-dist
Dynamic: requires-python
Dynamic: summary
